komaruscript/__init__.py
komaruscript/importer.py
komaruscript/main.py
komaruscript/transpiler.py
komaruscript/stdlib/__init__.py
komaruscript/stdlib/file_manager.py
komaruscript/stdlib/json_cat.py
komaruscript/stdlib/math_cat.py
komaruscript/stdlib/telegram_bot.py
komaruscript/stdlib/web_requests.py
komaruscript-2.1.0.dist-info/METADATA
komaruscript-2.1.0.dist-info/WHEEL
komaruscript-2.1.0.dist-info/entry_points.txt
komaruscript-2.1.0.dist-info/top_level.txt
komaruscript-2.1.0.dist-info/RECORD
