Metadata-Version: 2.4
Name: komaruscript
Version: 2.1.0
Summary: A Python-based programming language with cat commands! 🐱
Author: KomaruEat
Classifier: Programming Language :: Python :: 3
Classifier: License :: OSI Approved :: MIT License
Classifier: Operating System :: OS Independent
Requires-Python: >=3.6
Requires-Dist: requests
Requires-Dist: pyTelegramBotAPI
Dynamic: author
Dynamic: classifier
Dynamic: description
Dynamic: description-content-type
Dynamic: requires-dist
Dynamic: requires-python
Dynamic: summary
